whispervideos/__init__.py
whispervideos/docs_creation.py
whispervideos/support_file.py
whispervideos/transcribe_video.py
whispervideos/video_proc.py
whispervideos/whispervid.py
whispervideos-0.0.2.dist-info/METADATA
whispervideos-0.0.2.dist-info/WHEEL
whispervideos-0.0.2.dist-info/top_level.txt
whispervideos-0.0.2.dist-info/RECORD
